qtgqlcodegen/__init__.py
qtgqlcodegen/cli.py
qtgqlcodegen/config.py
qtgqlcodegen/core/__init__.py
qtgqlcodegen/core/cppref.py
qtgqlcodegen/core/exceptions.py
qtgqlcodegen/core/graphql_ref.py
qtgqlcodegen/core/template.py
qtgqlcodegen/generator.py
qtgqlcodegen/operation/__init__.py
qtgqlcodegen/operation/definitions.py
qtgqlcodegen/operation/evaluation.py
qtgqlcodegen/operation/selections_injection.py
qtgqlcodegen/operation/template.py
qtgqlcodegen/operation/utils.py
qtgqlcodegen/py.typed
qtgqlcodegen/schema/__init__.py
qtgqlcodegen/schema/definitions.py
qtgqlcodegen/schema/evaluation.py
qtgqlcodegen/schema/template.py
qtgqlcodegen/templates/CMakeLists.jinja.cmake
qtgqlcodegen/templates/macros/concrete_type_fields.jinja.hpp
qtgqlcodegen/templates/macros/deserialize_concrete_field.jinja.hpp
qtgqlcodegen/templates/macros/initialize_proxy_field.jinja.hpp
qtgqlcodegen/templates/macros/iterate_type_condition.jinja.hpp
qtgqlcodegen/templates/macros/proxy_type_fields.jinja.hpp
qtgqlcodegen/templates/macros/serialize_input_variable.jinja.hpp
qtgqlcodegen/templates/macros/update_concrete_field.jinja.hpp
qtgqlcodegen/templates/macros/update_proxy_field.jinja.cpp
qtgqlcodegen/templates/operation.jinja.cpp
qtgqlcodegen/templates/operation.jinja.hpp
qtgqlcodegen/templates/schema.jinja.hpp
qtgqlcodegen/types.py
qtgqlcodegen/utils.py
qtgql-0.139.0.dist-info/LICENSE
qtgql-0.139.0.dist-info/METADATA
qtgql-0.139.0.dist-info/WHEEL
qtgql-0.139.0.dist-info/entry_points.txt
qtgql-0.139.0.dist-info/RECORD
