Metadata-Version: 2.1
Name: qtgql
Version: 0.139.0
Summary: Qt framework for building graphql driven QML applications
License: MIT
Author: Nir
Author-email: 88795475+nrbnlulu@users.noreply.github.com
Maintainer: Nir.J Benlulu
Maintainer-email: nrbnlulu@gmail.com
Requires-Python: >=3.8,<3.12
Classifier: License :: OSI Approved :: MIT License
Classifier: Programming Language :: Python :: 3
Classifier: Programming Language :: Python :: 3.8
Classifier: Programming Language :: Python :: 3.9
Classifier: Programming Language :: Python :: 3.10
Classifier: Programming Language :: Python :: 3.11
Requires-Dist: attrs (>=22.2.0)
Requires-Dist: conan (>=2.0.10,<3.0.0)
Requires-Dist: graphql-core (>=3.2.3,<4.0.0)
Requires-Dist: jinja2 (>=3.1.2,<4.0.0)
Requires-Dist: typer[all] (>=0.9.0,<0.10.0)
Project-URL: Documentation, https://nrbnlulu.github.io/qtgql/
Project-URL: Homepage, https://github.com/nrbnlulu/qtgql
